dframeio/__init__.py
dframeio/abstract.py
dframeio/filter.py
dframeio/parquet.py
dframeio/postgres.py
dframeio-0.3.0.dist-info/LICENSE
dframeio-0.3.0.dist-info/WHEEL
dframeio-0.3.0.dist-info/METADATA
dframeio-0.3.0.dist-info/RECORD
