Metadata-Version: 2.1
Name: dframeio
Version: 0.3.0
Summary: Read and write dataframes anywhere.
Home-page: https://github.com/chr1st1ank/dataframe-io
License: Apache-2.0
Author: Christian Krudewig
Author-email: chr1st1ank@krudewig-online.de
Requires-Python: >=3.7.1,<4.0
Classifier: Development Status :: 5 - Production/Stable
Classifier: Intended Audience :: Developers
Classifier: License :: OSI Approved :: Apache Software License
Classifier: Natural Language :: English
Classifier: Programming Language :: Python :: 3
Classifier: Programming Language :: Python :: 3.10
Classifier: Programming Language :: Python :: 3.7
Classifier: Programming Language :: Python :: 3.8
Classifier: Programming Language :: Python :: 3.9
Classifier: Topic :: Database
Provides-Extra: dev
Provides-Extra: doc
Provides-Extra: parquet
Provides-Extra: postgres
Provides-Extra: pyarrow
Provides-Extra: test
Requires-Dist: lark-parser (>=0.12.0,<0.13.0)
Requires-Dist: pandas (>=1.0.0,<2.0)
Requires-Dist: psycopg (>=3,<4); extra == "postgres"
Requires-Dist: pyarrow (>=4.0,<7.0); extra == "pyarrow" or extra == "parquet"
